PyBrainf_ck/__init__.py
PyBrainf_ck-1.0.0.dist-info/LICENSE.txt
PyBrainf_ck-1.0.0.dist-info/METADATA
PyBrainf_ck-1.0.0.dist-info/WHEEL
PyBrainf_ck-1.0.0.dist-info/top_level.txt
PyBrainf_ck-1.0.0.dist-info/RECORD
