Metadata-Version: 2.1
Name: PyBrainf-ck
Version: 1.0.0
Summary: A simple package which gives the brainfuck code for the passed Text.
Home-page: https://github.com/code-reaper08/PyBrainf_ck
Author: Vishwa.R
Author-email: v.i.s.h.w.a.08.11.2001@gmail.com
License: UNKNOWN
Keywords: BRAINFUCK
Platform: UNKNOWN
Classifier: Programming Language :: Python :: 3
Classifier: License :: OSI Approved :: MIT License
Classifier: Operating System :: OS Independent
Requires-Python: >=3.6
